{
  "legislative_session": "132",
  "identifier": "LD 1518",
  "title": "An Act To Clarify The Amount And Use Of Unallocated Balances In A School Administrative Unit Budget",
  "from_organization": "~{\"classification\": \"lower\"}",
  "classification": [
    "bill"
  ],
  "subject": [
    "ADJUSTMENTS",
    "SCHOOL FUNDING FORMULA",
    "UNALLOCATED BALANCES"
  ],
  "abstracts": [],
  "other_titles": [],
  "other_identifiers": [],
  "actions": [
    {
      "description": "Committee on Education and Cultural Affairs suggested and ordered printed.",
      "date": "2025-04-08",
      "organization_id": "~{\"classification\": \"lower\"}",
      "classification": [],
      "related_entities": [],
      "_processing": {
        "log_file_created": "2025-10-25T00:00:01Z"
      }
    },
    {
      "description": "The Bill was REFERRED to the Committee on EDUCATION AND CULTURAL AFFAIRS.",
      "date": "2025-04-08",
      "organization_id": "~{\"classification\": \"lower\"}",
      "classification": [
        "referral-committee"
      ],
      "related_entities": [],
      "_processing": {
        "log_file_created": "2025-10-25T00:00:01Z"
      }
    },
    {
      "description": "Sent for concurrence. ORDERED SENT FORTHWITH.",
      "date": "2025-04-08",
      "organization_id": "~{\"classification\": \"lower\"}",
      "classification": [],
      "related_entities": [],
      "_processing": {
        "log_file_created": "2025-10-25T00:00:01Z"
      }
    },
    {
      "description": "The Bill was REFERRED to the Committee on EDUCATION AND CULTURAL AFFAIRS in concurrence",
      "date": "2025-04-08",
      "organization_id": "~{\"classification\": \"upper\"}",
      "classification": [
        "referral-committee"
      ],
      "related_entities": [],
      "_processing": {
        "log_file_created": "2025-10-25T00:00:01Z"
      }
    },
    {
      "description": "Pursuant to Joint Rule 310.3 Placed in Legislative Files (DEAD)",
      "date": "2025-05-21",
      "organization_id": "~{\"classification\": \"upper\"}",
      "classification": [
        "failure"
      ],
      "related_entities": [],
      "_processing": {
        "log_file_created": "2025-10-25T00:00:01Z"
      }
    },
    {
      "description": "Work Session Held",
      "date": "2025-05-16T04:00:00+00:00",
      "organization_id": "~{\"classification\": \"legislature\"}",
      "classification": [],
      "related_entities": [],
      "_processing": {
        "log_file_created": "2025-10-25T00:00:01Z"
      }
    },
    {
      "description": "Voted - ONTP",
      "date": "2025-05-16T04:00:00+00:00",
      "organization_id": "~{\"classification\": \"legislature\"}",
      "classification": [],
      "related_entities": [],
      "_processing": {
        "log_file_created": "2025-10-25T00:00:01Z"
      }
    },
    {
      "description": "Reported Out - ONTP",
      "date": "2025-05-20T04:00:00+00:00",
      "organization_id": "~{\"classification\": \"legislature\"}",
      "classification": [],
      "related_entities": [],
      "_processing": {
        "log_file_created": "2025-10-25T00:00:01Z"
      }
    }
  ],
  "sponsorships": [
    {
      "name": "Sharon FROST",
      "classification": "primary",
      "entity_type": "person",
      "primary": true,
      "person_id": "~{\"chamber\": \"lower\", \"name\": \"Sharon FROST\"}",
      "organization_id": null
    },
    {
      "name": "Richard BRADSTREET",
      "classification": "cosponsor",
      "entity_type": "person",
      "primary": false,
      "person_id": "~{\"chamber\": \"upper\", \"name\": \"Richard BRADSTREET\"}",
      "organization_id": null
    },
    {
      "name": "Gary FRIEDMANN",
      "classification": "cosponsor",
      "entity_type": "person",
      "primary": false,
      "person_id": "~{\"chamber\": \"lower\", \"name\": \"Gary FRIEDMANN\"}",
      "organization_id": null
    },
    {
      "name": "Tavis HASENFUS",
      "classification": "cosponsor",
      "entity_type": "person",
      "primary": false,
      "person_id": "~{\"chamber\": \"lower\", \"name\": \"Tavis HASENFUS\"}",
      "organization_id": null
    },
    {
      "name": "Amy ROEDER",
      "classification": "cosponsor",
      "entity_type": "person",
      "primary": false,
      "person_id": "~{\"chamber\": \"lower\", \"name\": \"Amy ROEDER\"}",
      "organization_id": null
    }
  ],
  "related_bills": [],
  "versions": [
    {
      "note": "Documents and Disposition",
      "links": [
        {
          "url": "http://www.mainelegislature.org/legis/bills/getPDF.asp?paper=HP1003&item=1&snum=132",
          "media_type": "application/pdf"
        }
      ],
      "date": "",
      "classification": ""
    }
  ],
  "documents": [],
  "citations": [],
  "sources": [
    {
      "url": "https://legislature.maine.gov/LawMakerWeb/summary.asp?ID=280098327",
      "note": ""
    },
    {
      "url": "https://legislature.maine.gov/LawMakerWeb/sponsors.asp?ID=280098327",
      "note": ""
    },
    {
      "url": "https://legislature.maine.gov/LawMakerWeb/dockets.asp?ID=280098327",
      "note": ""
    },
    {
      "url": "https://legislature.maine.gov/LawMakerWeb/subjects.asp?ID=280098327",
      "note": ""
    }
  ],
  "extras": {
    "ld_number": "LD 1518"
  },
  "jurisdiction": {
    "id": "ocd-jurisdiction/country:us/state:me/government",
    "name": "Maine",
    "classification": "state",
    "division_id": "ocd-division/country:us/state:me"
  },
  "_processing": {
    "logs_latest_update": "2025-10-25T00:00:01Z",
    "text_extraction_latest_update": "2025-10-29T05:03:20.798570Z"
  }
}