{
  "legislative_session": "132",
  "identifier": "LD 1557",
  "title": "An Act To Ensure Uniformity In The Regulation Of Perfluoroalkyl And Polyfluoroalkyl Substances In Pesticides",
  "from_organization": "~{\"classification\": \"lower\"}",
  "classification": [
    "bill"
  ],
  "subject": [
    "MANAGEMENT",
    "PESTICIDES",
    "UNIFORM PRACTICES"
  ],
  "abstracts": [],
  "other_titles": [],
  "other_identifiers": [],
  "actions": [
    {
      "description": "Committee on AGRICULTURE, CONSERVATION AND FORESTRY suggested and ordered printed.",
      "date": "2025-04-10",
      "organization_id": "~{\"classification\": \"lower\"}",
      "classification": [],
      "related_entities": [],
      "_processing": {
        "log_file_created": "2025-10-25T00:00:01Z"
      }
    },
    {
      "description": "Representative PLUECKER of Warren, MOVED to REFER the Bill to the Committee on ENVIRONMENT AND NATURAL RESOURCES.",
      "date": "2025-04-10",
      "organization_id": "~{\"classification\": \"lower\"}",
      "classification": [],
      "related_entities": [],
      "_processing": {
        "log_file_created": "2025-10-25T00:00:01Z"
      }
    },
    {
      "description": "On motion of Representative ARATA of New Gloucester, TABLED pending REFERENCE to the Committee on ENVIRONMENT AND NATURAL RESOURCES.",
      "date": "2025-04-10",
      "organization_id": "~{\"classification\": \"lower\"}",
      "classification": [],
      "related_entities": [],
      "_processing": {
        "log_file_created": "2025-10-25T00:00:01Z"
      }
    },
    {
      "description": "Later today assigned.",
      "date": "2025-04-10",
      "organization_id": "~{\"classification\": \"lower\"}",
      "classification": [],
      "related_entities": [],
      "_processing": {
        "log_file_created": "2025-10-25T00:00:01Z"
      }
    },
    {
      "description": "Speaker laid before the House",
      "date": "2025-04-10",
      "organization_id": "~{\"classification\": \"lower\"}",
      "classification": [],
      "related_entities": [],
      "_processing": {
        "log_file_created": "2025-10-25T00:00:01Z"
      }
    },
    {
      "description": "Subsequently, the Bill was REFERRED to the Committee on ENVIRONMENT AND NATURAL RESOURCES.",
      "date": "2025-04-10",
      "organization_id": "~{\"classification\": \"lower\"}",
      "classification": [
        "referral-committee"
      ],
      "related_entities": [],
      "_processing": {
        "log_file_created": "2025-10-25T00:00:01Z"
      }
    },
    {
      "description": "Sent for concurrence. ORDERED SENT FORTHWITH.",
      "date": "2025-04-10",
      "organization_id": "~{\"classification\": \"lower\"}",
      "classification": [],
      "related_entities": [],
      "_processing": {
        "log_file_created": "2025-10-25T00:00:01Z"
      }
    },
    {
      "description": "On motion by Senator TALBOT ROSS of Cumberland The Bill was REFERRED to the Committee on AGRICULTURE, CONSERVATION AND FORESTRY In NON-CONCURRENCE",
      "date": "2025-04-15",
      "organization_id": "~{\"classification\": \"upper\"}",
      "classification": [
        "referral-committee"
      ],
      "related_entities": [],
      "_processing": {
        "log_file_created": "2025-10-25T00:00:01Z"
      }
    },
    {
      "description": "Sent down for concurrence",
      "date": "2025-04-15",
      "organization_id": "~{\"classification\": \"upper\"}",
      "classification": [],
      "related_entities": [],
      "_processing": {
        "log_file_created": "2025-10-25T00:00:01Z"
      }
    },
    {
      "description": "The House INSISTED on REFERENCE to the Committee on ENVIRONMENT AND NATURAL RESOURCES.",
      "date": "2025-04-17",
      "organization_id": "~{\"classification\": \"lower\"}",
      "classification": [],
      "related_entities": [],
      "_processing": {
        "log_file_created": "2025-10-25T00:00:01Z"
      }
    },
    {
      "description": "ORDERED SENT FORTHWITH.",
      "date": "2025-04-17",
      "organization_id": "~{\"classification\": \"lower\"}",
      "classification": [],
      "related_entities": [],
      "_processing": {
        "log_file_created": "2025-10-25T00:00:01Z"
      }
    },
    {
      "description": "On motion by Senator PIERCE of Cumberland The Senate INSISTED on REFERENCE to the Committee on AGRICULTURE, CONSERVATION AND FORESTRY",
      "date": "2025-04-22",
      "organization_id": "~{\"classification\": \"upper\"}",
      "classification": [],
      "related_entities": [],
      "_processing": {
        "log_file_created": "2025-10-25T00:00:01Z"
      }
    },
    {
      "description": "Placed in Legislative Files (DEAD)",
      "date": "2025-04-22",
      "organization_id": "~{\"classification\": \"upper\"}",
      "classification": [
        "failure"
      ],
      "related_entities": [],
      "_processing": {
        "log_file_created": "2025-10-25T00:00:01Z"
      }
    }
  ],
  "sponsorships": [
    {
      "name": "Amy ARATA",
      "classification": "primary",
      "entity_type": "person",
      "primary": true,
      "person_id": "~{\"chamber\": \"lower\", \"name\": \"Amy ARATA\"}",
      "organization_id": null
    },
    {
      "name": "Susan BERNARD",
      "classification": "cosponsor",
      "entity_type": "person",
      "primary": false,
      "person_id": "~{\"chamber\": \"upper\", \"name\": \"Susan BERNARD\"}",
      "organization_id": null
    },
    {
      "name": "Mark COOPER",
      "classification": "cosponsor",
      "entity_type": "person",
      "primary": false,
      "person_id": "~{\"chamber\": \"lower\", \"name\": \"Mark COOPER\"}",
      "organization_id": null
    },
    {
      "name": "Dean CRAY",
      "classification": "cosponsor",
      "entity_type": "person",
      "primary": false,
      "person_id": "~{\"chamber\": \"lower\", \"name\": \"Dean CRAY\"}",
      "organization_id": null
    },
    {
      "name": "James DILL",
      "classification": "cosponsor",
      "entity_type": "person",
      "primary": false,
      "person_id": "~{\"chamber\": \"lower\", \"name\": \"James DILL\"}",
      "organization_id": null
    },
    {
      "name": "Timothy GUERRETTE",
      "classification": "cosponsor",
      "entity_type": "person",
      "primary": false,
      "person_id": "~{\"chamber\": \"lower\", \"name\": \"Timothy GUERRETTE\"}",
      "organization_id": null
    },
    {
      "name": "Allison HEPLER",
      "classification": "cosponsor",
      "entity_type": "person",
      "primary": false,
      "person_id": "~{\"chamber\": \"lower\", \"name\": \"Allison HEPLER\"}",
      "organization_id": null
    },
    {
      "name": "Caldwell JACKSON",
      "classification": "cosponsor",
      "entity_type": "person",
      "primary": false,
      "person_id": "~{\"chamber\": \"lower\", \"name\": \"Caldwell JACKSON\"}",
      "organization_id": null
    }
  ],
  "related_bills": [],
  "versions": [
    {
      "note": "Documents and Disposition",
      "links": [
        {
          "url": "http://www.mainelegislature.org/legis/bills/getPDF.asp?paper=HP1015&item=1&snum=132",
          "media_type": "application/pdf"
        }
      ],
      "date": "",
      "classification": ""
    }
  ],
  "documents": [],
  "citations": [],
  "sources": [
    {
      "url": "https://legislature.maine.gov/LawMakerWeb/summary.asp?ID=280098377",
      "note": ""
    },
    {
      "url": "https://legislature.maine.gov/LawMakerWeb/sponsors.asp?ID=280098377",
      "note": ""
    },
    {
      "url": "https://legislature.maine.gov/LawMakerWeb/dockets.asp?ID=280098377",
      "note": ""
    },
    {
      "url": "https://legislature.maine.gov/LawMakerWeb/subjects.asp?ID=280098377",
      "note": ""
    }
  ],
  "extras": {
    "ld_number": "LD 1557"
  },
  "jurisdiction": {
    "id": "ocd-jurisdiction/country:us/state:me/government",
    "name": "Maine",
    "classification": "state",
    "division_id": "ocd-division/country:us/state:me"
  },
  "_processing": {
    "logs_latest_update": "2025-10-25T00:00:01Z"
  }
}