{
  "legislative_session": "132",
  "identifier": "SP 183",
  "title": "Joint Resolution Recognizing February 2025 As Black History Month",
  "from_organization": "~{\"classification\": \"upper\"}",
  "classification": [
    "joint resolution"
  ],
  "subject": [],
  "abstracts": [],
  "other_titles": [],
  "other_identifiers": [],
  "actions": [
    {
      "description": "On motion by Senator TALBOT ROSS of Cumberland READ and ADOPTED.",
      "date": "2025-02-04",
      "organization_id": "~{\"classification\": \"upper\"}",
      "classification": [
        "passage"
      ],
      "related_entities": [],
      "_processing": {
        "log_file_created": "2025-10-25T00:00:05Z"
      }
    },
    {
      "description": "Ordered sent down forthwith for concurrence.",
      "date": "2025-02-04",
      "organization_id": "~{\"classification\": \"upper\"}",
      "classification": [],
      "related_entities": [],
      "_processing": {
        "log_file_created": "2025-10-25T00:00:05Z"
      }
    },
    {
      "description": "READ and ADOPTED.",
      "date": "2025-02-11",
      "organization_id": "~{\"classification\": \"lower\"}",
      "classification": [
        "passage"
      ],
      "related_entities": [],
      "_processing": {
        "log_file_created": "2025-10-25T00:00:05Z"
      }
    },
    {
      "description": "In concurrence. ORDERED SENT FORTHWITH.",
      "date": "2025-02-11",
      "organization_id": "~{\"classification\": \"lower\"}",
      "classification": [],
      "related_entities": [],
      "_processing": {
        "log_file_created": "2025-10-25T00:00:05Z"
      }
    }
  ],
  "sponsorships": [
    {
      "name": "Rachel TALBOT ROSS",
      "classification": "primary",
      "entity_type": "person",
      "primary": true,
      "person_id": "~{\"chamber\": \"upper\", \"name\": \"Rachel TALBOT ROSS\"}",
      "organization_id": null
    },
    {
      "name": "Mana ABDI",
      "classification": "cosponsor",
      "entity_type": "person",
      "primary": false,
      "person_id": "~{\"chamber\": \"lower\", \"name\": \"Mana ABDI\"}",
      "organization_id": null
    },
    {
      "name": "Flavia DEBRITO",
      "classification": "cosponsor",
      "entity_type": "person",
      "primary": false,
      "person_id": "~{\"chamber\": \"lower\", \"name\": \"Flavia DEBRITO\"}",
      "organization_id": null
    },
    {
      "name": "Deqa DHALAC",
      "classification": "cosponsor",
      "entity_type": "person",
      "primary": false,
      "person_id": "~{\"chamber\": \"lower\", \"name\": \"Deqa DHALAC\"}",
      "organization_id": null
    },
    {
      "name": "Jill DUSON",
      "classification": "cosponsor",
      "entity_type": "person",
      "primary": false,
      "person_id": "~{\"chamber\": \"upper\", \"name\": \"Jill DUSON\"}",
      "organization_id": null
    },
    {
      "name": "Craig HICKMAN",
      "classification": "cosponsor",
      "entity_type": "person",
      "primary": false,
      "person_id": "~{\"chamber\": \"upper\", \"name\": \"Craig HICKMAN\"}",
      "organization_id": null
    },
    {
      "name": "Rafael MACIAS",
      "classification": "cosponsor",
      "entity_type": "person",
      "primary": false,
      "person_id": "~{\"chamber\": \"lower\", \"name\": \"Rafael MACIAS\"}",
      "organization_id": null
    },
    {
      "name": "Ambureen RANA",
      "classification": "cosponsor",
      "entity_type": "person",
      "primary": false,
      "person_id": "~{\"chamber\": \"lower\", \"name\": \"Ambureen RANA\"}",
      "organization_id": null
    },
    {
      "name": "Eleanor SATO",
      "classification": "cosponsor",
      "entity_type": "person",
      "primary": false,
      "person_id": "~{\"chamber\": \"lower\", \"name\": \"Eleanor SATO\"}",
      "organization_id": null
    },
    {
      "name": "Yusuf YUSUF",
      "classification": "cosponsor",
      "entity_type": "person",
      "primary": false,
      "person_id": "~{\"chamber\": \"lower\", \"name\": \"Yusuf YUSUF\"}",
      "organization_id": null
    }
  ],
  "related_bills": [],
  "versions": [
    {
      "note": "Documents and Disposition",
      "links": [
        {
          "url": "http://www.mainelegislature.org/legis/bills/getPDF.asp?paper=SP0183&item=1&snum=132",
          "media_type": "application/pdf"
        }
      ],
      "date": "",
      "classification": ""
    }
  ],
  "documents": [],
  "citations": [],
  "sources": [
    {
      "url": "https://legislature.maine.gov/LawMakerWeb/summary.asp?ID=280096297",
      "note": ""
    },
    {
      "url": "https://legislature.maine.gov/LawMakerWeb/sponsors.asp?ID=280096297",
      "note": ""
    },
    {
      "url": "https://legislature.maine.gov/LawMakerWeb/dockets.asp?ID=280096297",
      "note": ""
    },
    {
      "url": "https://legislature.maine.gov/LawMakerWeb/subjects.asp?ID=280096297",
      "note": ""
    }
  ],
  "extras": {},
  "jurisdiction": {
    "id": "ocd-jurisdiction/country:us/state:me/government",
    "name": "Maine",
    "classification": "state",
    "division_id": "ocd-division/country:us/state:me"
  },
  "_processing": {
    "logs_latest_update": "2025-10-25T00:00:05Z",
    "text_extraction_latest_update": "2025-10-29T05:46:48.000541Z"
  }
}