{
  "legislative_session": "132",
  "identifier": "LD 1962",
  "title": "An Act To Establish The Corrections Ombudsman",
  "from_organization": "~{\"classification\": \"upper\"}",
  "classification": [
    "bill"
  ],
  "subject": [
    "ADMINISTRATION",
    "CORRECTIONS DEPT",
    "CORRECTIONS OMBUDSMAN"
  ],
  "abstracts": [],
  "other_titles": [],
  "other_identifiers": [],
  "actions": [
    {
      "description": "Committee on CRIMINAL JUSTICE AND PUBLIC SAFETY suggested and ordered printed REFERENCE to the Committee on CRIMINAL JUSTICE AND PUBLIC SAFETY Ordered sent down forthwith for concurrence",
      "date": "2025-05-13",
      "organization_id": "~{\"classification\": \"upper\"}",
      "classification": [],
      "related_entities": [],
      "_processing": {
        "log_file_created": "2025-10-25T00:00:02Z"
      }
    },
    {
      "description": "The Bill was REFERRED to the Committee on CRIMINAL JUSTICE AND PUBLIC SAFETY.",
      "date": "2025-05-13",
      "organization_id": "~{\"classification\": \"lower\"}",
      "classification": [
        "referral-committee"
      ],
      "related_entities": [],
      "_processing": {
        "log_file_created": "2025-10-25T00:00:02Z"
      }
    },
    {
      "description": "In concurrence. ORDERED SENT FORTHWITH.",
      "date": "2025-05-13",
      "organization_id": "~{\"classification\": \"lower\"}",
      "classification": [],
      "related_entities": [],
      "_processing": {
        "log_file_created": "2025-10-25T00:00:02Z"
      }
    },
    {
      "description": "CARRIED OVER, in the same posture, to any special or regular session of the 132nd Legislature, pursuant to Joint Order SP 800.",
      "date": "2025-06-25",
      "organization_id": "~{\"classification\": \"upper\"}",
      "classification": [],
      "related_entities": [],
      "_processing": {
        "log_file_created": "2025-10-25T00:00:02Z"
      }
    },
    {
      "description": "Work Session Held - TABLED",
      "date": "2025-05-15T04:00:00+00:00",
      "organization_id": "~{\"classification\": \"legislature\"}",
      "classification": [],
      "related_entities": [],
      "_processing": {
        "log_file_created": "2025-10-25T00:00:02Z"
      }
    },
    {
      "description": "Carry Over Requested",
      "date": "2025-05-16T04:00:00+00:00",
      "organization_id": "~{\"classification\": \"legislature\"}",
      "classification": [],
      "related_entities": [],
      "_processing": {
        "log_file_created": "2025-10-25T00:00:02Z"
      }
    },
    {
      "description": "Carry Over Approved",
      "date": "2025-05-19T04:00:00+00:00",
      "organization_id": "~{\"classification\": \"legislature\"}",
      "classification": [],
      "related_entities": [],
      "_processing": {
        "log_file_created": "2025-10-25T00:00:02Z"
      }
    }
  ],
  "sponsorships": [
    {
      "name": "Jill DUSON",
      "classification": "primary",
      "entity_type": "person",
      "primary": true,
      "person_id": "~{\"chamber\": \"upper\", \"name\": \"Jill DUSON\"}",
      "organization_id": null
    },
    {
      "name": "Richard BENNETT",
      "classification": "cosponsor",
      "entity_type": "person",
      "primary": false,
      "person_id": "~{\"chamber\": \"upper\", \"name\": \"Richard BENNETT\"}",
      "organization_id": null
    },
    {
      "name": "Tavis HASENFUS",
      "classification": "cosponsor",
      "entity_type": "person",
      "primary": false,
      "person_id": "~{\"chamber\": \"lower\", \"name\": \"Tavis HASENFUS\"}",
      "organization_id": null
    },
    {
      "name": "Nina MILLIKEN",
      "classification": "cosponsor",
      "entity_type": "person",
      "primary": false,
      "person_id": "~{\"chamber\": \"lower\", \"name\": \"Nina MILLIKEN\"}",
      "organization_id": null
    },
    {
      "name": "Rachel TALBOT ROSS",
      "classification": "cosponsor",
      "entity_type": "person",
      "primary": false,
      "person_id": "~{\"chamber\": \"upper\", \"name\": \"Rachel TALBOT ROSS\"}",
      "organization_id": null
    }
  ],
  "related_bills": [],
  "versions": [
    {
      "note": "Documents and Disposition",
      "links": [
        {
          "url": "http://www.mainelegislature.org/legis/bills/getPDF.asp?paper=SP0769&item=1&snum=132",
          "media_type": "application/pdf"
        }
      ],
      "date": "",
      "classification": ""
    }
  ],
  "documents": [],
  "citations": [],
  "sources": [
    {
      "url": "https://legislature.maine.gov/LawMakerWeb/summary.asp?ID=280099214",
      "note": ""
    },
    {
      "url": "https://legislature.maine.gov/LawMakerWeb/sponsors.asp?ID=280099214",
      "note": ""
    },
    {
      "url": "https://legislature.maine.gov/LawMakerWeb/dockets.asp?ID=280099214",
      "note": ""
    },
    {
      "url": "https://legislature.maine.gov/LawMakerWeb/subjects.asp?ID=280099214",
      "note": ""
    }
  ],
  "extras": {
    "ld_number": "LD 1962"
  },
  "jurisdiction": {
    "id": "ocd-jurisdiction/country:us/state:me/government",
    "name": "Maine",
    "classification": "state",
    "division_id": "ocd-division/country:us/state:me"
  },
  "_processing": {
    "logs_latest_update": "2025-10-25T00:00:02Z",
    "text_extraction_latest_update": "2025-10-26T06:57:08.050950Z"
  }
}