{
  "legislative_session": "132",
  "identifier": "LD 1150",
  "title": "An Act To Require Reporting Of Sheltering Or Aiding Missing Children",
  "from_organization": "~{\"classification\": \"lower\"}",
  "classification": [
    "bill"
  ],
  "subject": [
    "LAW ENFORCEMENT",
    "MISSING PERSONS",
    "RUNAWAY CHILDREN"
  ],
  "abstracts": [],
  "other_titles": [],
  "other_identifiers": [],
  "actions": [
    {
      "description": "Committee on Criminal Justice and Public Safety suggested and ordered printed.",
      "date": "2025-03-20",
      "organization_id": "~{\"classification\": \"lower\"}",
      "classification": [],
      "related_entities": [],
      "_processing": {
        "log_file_created": "2025-10-25T00:00:01Z"
      }
    },
    {
      "description": "The Bill was REFERRED to the Committee on CRIMINAL JUSTICE AND PUBLIC SAFETY.",
      "date": "2025-03-20",
      "organization_id": "~{\"classification\": \"lower\"}",
      "classification": [
        "referral-committee"
      ],
      "related_entities": [],
      "_processing": {
        "log_file_created": "2025-10-25T00:00:01Z"
      }
    },
    {
      "description": "Sent for concurrence. ORDERED SENT FORTHWITH.",
      "date": "2025-03-20",
      "organization_id": "~{\"classification\": \"lower\"}",
      "classification": [],
      "related_entities": [],
      "_processing": {
        "log_file_created": "2025-10-25T00:00:01Z"
      }
    },
    {
      "description": "The Bill was REFERRED to the Committee on CRIMINAL JUSTICE AND PUBLIC SAFETY in concurrence",
      "date": "2025-03-20",
      "organization_id": "~{\"classification\": \"upper\"}",
      "classification": [
        "referral-committee"
      ],
      "related_entities": [],
      "_processing": {
        "log_file_created": "2025-10-25T00:00:01Z"
      }
    },
    {
      "description": "Carried over, in the same posture, to the next special or regular session of the 132nd Legislature, pursuant to Joint Order SP 519.",
      "date": "2025-03-21",
      "organization_id": "~{\"classification\": \"lower\"}",
      "classification": [],
      "related_entities": [],
      "_processing": {
        "log_file_created": "2025-10-25T00:00:01Z"
      }
    },
    {
      "description": "CONSENT CALENDAR - FIRST DAY",
      "date": "2025-04-24",
      "organization_id": "~{\"classification\": \"lower\"}",
      "classification": [],
      "related_entities": [],
      "_processing": {
        "log_file_created": "2025-10-25T00:00:01Z"
      }
    },
    {
      "description": "Under suspension of the rules CONSENT CALENDAR - SECOND DAY.",
      "date": "2025-04-24",
      "organization_id": "~{\"classification\": \"lower\"}",
      "classification": [],
      "related_entities": [],
      "_processing": {
        "log_file_created": "2025-10-25T00:00:01Z"
      }
    },
    {
      "description": "The Bill was PASSED TO BE ENGROSSED.",
      "date": "2025-04-24",
      "organization_id": "~{\"classification\": \"lower\"}",
      "classification": [
        "reading-3"
      ],
      "related_entities": [],
      "_processing": {
        "log_file_created": "2025-10-25T00:00:01Z"
      }
    },
    {
      "description": "Sent for concurrence. ORDERED SENT FORTHWITH.",
      "date": "2025-04-24",
      "organization_id": "~{\"classification\": \"lower\"}",
      "classification": [],
      "related_entities": [],
      "_processing": {
        "log_file_created": "2025-10-25T00:00:01Z"
      }
    },
    {
      "description": "Report READ and ACCEPTED, in concurrence.",
      "date": "2025-04-29",
      "organization_id": "~{\"classification\": \"upper\"}",
      "classification": [],
      "related_entities": [],
      "_processing": {
        "log_file_created": "2025-10-25T00:00:01Z"
      }
    },
    {
      "description": "READ ONCE",
      "date": "2025-04-29",
      "organization_id": "~{\"classification\": \"upper\"}",
      "classification": [
        "reading-1"
      ],
      "related_entities": [],
      "_processing": {
        "log_file_created": "2025-10-25T00:00:01Z"
      }
    },
    {
      "description": "Under suspension of the Rules, READ A SECOND TIME and PASSED TO BE ENGROSSED, in concurrence.",
      "date": "2025-04-29",
      "organization_id": "~{\"classification\": \"upper\"}",
      "classification": [
        "reading-2",
        "reading-3"
      ],
      "related_entities": [],
      "_processing": {
        "log_file_created": "2025-10-25T00:00:01Z"
      }
    },
    {
      "description": "Ordered sent down forthwith.",
      "date": "2025-04-29",
      "organization_id": "~{\"classification\": \"upper\"}",
      "classification": [],
      "related_entities": [],
      "_processing": {
        "log_file_created": "2025-10-25T00:00:01Z"
      }
    },
    {
      "description": "PASSED TO BE ENACTED.",
      "date": "2025-04-30",
      "organization_id": "~{\"classification\": \"lower\"}",
      "classification": [
        "passage"
      ],
      "related_entities": [],
      "_processing": {
        "log_file_created": "2025-10-25T00:00:01Z"
      }
    },
    {
      "description": "Sent for concurrence. ORDERED SENT FORTHWITH.",
      "date": "2025-04-30",
      "organization_id": "~{\"classification\": \"lower\"}",
      "classification": [],
      "related_entities": [],
      "_processing": {
        "log_file_created": "2025-10-25T00:00:01Z"
      }
    },
    {
      "description": "PASSED TO BE ENACTED, in concurrence.",
      "date": "2025-05-06",
      "organization_id": "~{\"classification\": \"upper\"}",
      "classification": [
        "passage"
      ],
      "related_entities": [],
      "_processing": {
        "log_file_created": "2025-10-25T00:00:01Z"
      }
    },
    {
      "description": "Signed by Governor",
      "date": "2025-05-09",
      "organization_id": "~{\"classification\": \"executive\"}",
      "classification": [
        "executive-signature"
      ],
      "related_entities": [],
      "_processing": {
        "log_file_created": "2025-10-25T00:00:01Z"
      }
    },
    {
      "description": "Work Session Held",
      "date": "2025-04-16T04:00:00+00:00",
      "organization_id": "~{\"classification\": \"legislature\"}",
      "classification": [],
      "related_entities": [],
      "_processing": {
        "log_file_created": "2025-10-25T00:00:01Z"
      }
    },
    {
      "description": "Voted - OTP",
      "date": "2025-04-16T04:00:00+00:00",
      "organization_id": "~{\"classification\": \"legislature\"}",
      "classification": [],
      "related_entities": [],
      "_processing": {
        "log_file_created": "2025-10-25T00:00:01Z"
      }
    },
    {
      "description": "Reported Out - OTP",
      "date": "2025-04-22T04:00:00+00:00",
      "organization_id": "~{\"classification\": \"legislature\"}",
      "classification": [],
      "related_entities": [],
      "_processing": {
        "log_file_created": "2025-10-25T00:00:01Z"
      }
    }
  ],
  "sponsorships": [],
  "related_bills": [],
  "versions": [
    {
      "note": "Documents and Disposition",
      "links": [
        {
          "url": "http://www.mainelegislature.org/legis/bills/getPDF.asp?paper=HP0755&item=1&snum=132",
          "media_type": "application/pdf"
        }
      ],
      "date": "",
      "classification": ""
    },
    {
      "note": "Final Disposition",
      "links": [
        {
          "url": "http://www.mainelegislature.org/legis/bills/getPDF.asp?paper=HP0755&item=2&snum=132",
          "media_type": "application/pdf"
        }
      ],
      "date": "",
      "classification": ""
    }
  ],
  "documents": [
    {
      "note": "Documents and Disposition - Fiscal Note PDF",
      "links": [
        {
          "url": "http://www.mainelegislature.org/legis/bills/bills_132nd/fiscalpdfs/FN115001.pdf",
          "media_type": "application/pdf"
        }
      ],
      "date": "",
      "classification": ""
    },
    {
      "note": "Documents and Disposition - Fiscal Note HTML",
      "links": [
        {
          "url": "http://www.mainelegislature.org/legis/bills/bills_132nd/fiscalnotes/FN115001.htm",
          "media_type": "text/html"
        }
      ],
      "date": "",
      "classification": ""
    },
    {
      "note": "Final Disposition - Fiscal Note PDF",
      "links": [
        {
          "url": "http://www.mainelegislature.org/legis/bills/bills_132nd/fiscalpdfs/FN115002.pdf",
          "media_type": "application/pdf"
        }
      ],
      "date": "",
      "classification": ""
    },
    {
      "note": "Final Disposition - Fiscal Note HTML",
      "links": [
        {
          "url": "http://www.mainelegislature.org/legis/bills/bills_132nd/fiscalnotes/FN115002.htm",
          "media_type": "text/html"
        }
      ],
      "date": "",
      "classification": ""
    }
  ],
  "citations": [],
  "sources": [
    {
      "url": "https://legislature.maine.gov/LawMakerWeb/summary.asp?ID=280097658",
      "note": ""
    },
    {
      "url": "https://legislature.maine.gov/LawMakerWeb/sponsors.asp?ID=280097658",
      "note": ""
    },
    {
      "url": "https://legislature.maine.gov/LawMakerWeb/dockets.asp?ID=280097658",
      "note": ""
    },
    {
      "url": "https://legislature.maine.gov/LawMakerWeb/subjects.asp?ID=280097658",
      "note": ""
    }
  ],
  "extras": {
    "ld_number": "LD 1150"
  },
  "jurisdiction": {
    "id": "ocd-jurisdiction/country:us/state:me/government",
    "name": "Maine",
    "classification": "state",
    "division_id": "ocd-division/country:us/state:me"
  },
  "_processing": {
    "logs_latest_update": "2025-10-25T00:00:01Z",
    "text_extraction_latest_update": "2025-10-29T04:16:18.780482Z"
  }
}