{
  "legislative_session": "132",
  "identifier": "LD 1728",
  "title": "An Act To Establish The Maine Child Care Affordability Program Advisory Board",
  "from_organization": "~{\"classification\": \"upper\"}",
  "classification": [
    "bill"
  ],
  "subject": [
    "CHILD CARE",
    "CHILDREN AND FAMILIES",
    "WORKFORCE"
  ],
  "abstracts": [],
  "other_titles": [],
  "other_identifiers": [],
  "actions": [
    {
      "description": "Committee on HEALTH AND HUMAN SERVICES suggested and ordered printed REFERENCE to the Committee on HEALTH AND HUMAN SERVICES Ordered sent down forthwith for concurrence",
      "date": "2025-04-17",
      "organization_id": "~{\"classification\": \"upper\"}",
      "classification": [],
      "related_entities": [],
      "_processing": {
        "log_file_created": "2025-10-25T00:00:06Z"
      }
    },
    {
      "description": "The Bill was REFERRED to the Committee on HEALTH AND HUMAN SERVICES.",
      "date": "2025-04-17",
      "organization_id": "~{\"classification\": \"lower\"}",
      "classification": [
        "referral-committee"
      ],
      "related_entities": [],
      "_processing": {
        "log_file_created": "2025-10-25T00:00:06Z"
      }
    },
    {
      "description": "In concurrence. ORDERED SENT FORTHWITH.",
      "date": "2025-04-17",
      "organization_id": "~{\"classification\": \"lower\"}",
      "classification": [],
      "related_entities": [],
      "_processing": {
        "log_file_created": "2025-10-25T00:00:06Z"
      }
    },
    {
      "description": "CARRIED OVER, in the same posture, to any special or regular session of the 132nd Legislature, pursuant to Joint Order SP 800.",
      "date": "2025-06-25",
      "organization_id": "~{\"classification\": \"upper\"}",
      "classification": [],
      "related_entities": [],
      "_processing": {
        "log_file_created": "2025-10-25T00:00:06Z"
      }
    },
    {
      "description": "Work Session Held - TABLED",
      "date": "2025-05-22T04:00:00+00:00",
      "organization_id": "~{\"classification\": \"legislature\"}",
      "classification": [],
      "related_entities": [],
      "_processing": {
        "log_file_created": "2025-10-25T00:00:06Z"
      }
    },
    {
      "description": "Carry Over Requested",
      "date": "2025-05-23T04:00:00+00:00",
      "organization_id": "~{\"classification\": \"legislature\"}",
      "classification": [],
      "related_entities": [],
      "_processing": {
        "log_file_created": "2025-10-25T00:00:06Z"
      }
    },
    {
      "description": "Carry Over Approved",
      "date": "2025-06-25T04:00:00+00:00",
      "organization_id": "~{\"classification\": \"legislature\"}",
      "classification": [],
      "related_entities": [],
      "_processing": {
        "log_file_created": "2025-10-25T00:00:06Z"
      }
    }
  ],
  "sponsorships": [
    {
      "name": "Henry INGWERSEN",
      "classification": "primary",
      "entity_type": "person",
      "primary": true,
      "person_id": "~{\"chamber\": \"upper\", \"name\": \"Henry INGWERSEN\"}",
      "organization_id": null
    },
    {
      "name": "Matthea DAUGHTRY",
      "classification": "cosponsor",
      "entity_type": "person",
      "primary": false,
      "person_id": "~{\"chamber\": \"upper\", \"name\": \"Matthea DAUGHTRY\"}",
      "organization_id": null
    },
    {
      "name": "Anne GRAHAM",
      "classification": "cosponsor",
      "entity_type": "person",
      "primary": false,
      "person_id": "~{\"chamber\": \"lower\", \"name\": \"Anne GRAHAM\"}",
      "organization_id": null
    },
    {
      "name": "Timothy NANGLE",
      "classification": "cosponsor",
      "entity_type": "person",
      "primary": false,
      "person_id": "~{\"chamber\": \"upper\", \"name\": \"Timothy NANGLE\"}",
      "organization_id": null
    },
    {
      "name": "Cameron RENY",
      "classification": "cosponsor",
      "entity_type": "person",
      "primary": false,
      "person_id": "~{\"chamber\": \"upper\", \"name\": \"Cameron RENY\"}",
      "organization_id": null
    }
  ],
  "related_bills": [],
  "versions": [
    {
      "note": "Documents and Disposition",
      "links": [
        {
          "url": "http://www.mainelegislature.org/legis/bills/getPDF.asp?paper=SP0674&item=1&snum=132",
          "media_type": "application/pdf"
        }
      ],
      "date": "",
      "classification": ""
    }
  ],
  "documents": [],
  "citations": [],
  "sources": [
    {
      "url": "https://legislature.maine.gov/LawMakerWeb/summary.asp?ID=280098628",
      "note": ""
    },
    {
      "url": "https://legislature.maine.gov/LawMakerWeb/sponsors.asp?ID=280098628",
      "note": ""
    },
    {
      "url": "https://legislature.maine.gov/LawMakerWeb/dockets.asp?ID=280098628",
      "note": ""
    },
    {
      "url": "https://legislature.maine.gov/LawMakerWeb/subjects.asp?ID=280098628",
      "note": ""
    }
  ],
  "extras": {
    "ld_number": "LD 1728"
  },
  "jurisdiction": {
    "id": "ocd-jurisdiction/country:us/state:me/government",
    "name": "Maine",
    "classification": "state",
    "division_id": "ocd-division/country:us/state:me"
  },
  "_processing": {
    "logs_latest_update": "2025-10-25T00:00:06Z",
    "text_extraction_latest_update": "2025-10-26T06:37:38.746908Z"
  }
}